wtg_cli/__init__.py
wtg_cli/__main__.py
wtg_cli/_wtg.cpython-311-x86_64-linux-gnu.so
wtg_cli/cli.py
wtg_cli-0.3.0.dist-info/METADATA
wtg_cli-0.3.0.dist-info/WHEEL
wtg_cli-0.3.0.dist-info/entry_points.txt
wtg_cli-0.3.0.dist-info/licenses/LICENSE
wtg_cli.libs/libcom_err-2abe824b.so.2
wtg_cli.libs/libcrypto-d3570994.so.10
wtg_cli.libs/libgssapi_krb5-497db0c6.so.2
wtg_cli.libs/libk5crypto-b1f99d5c.so.3
wtg_cli.libs/libkeyutils-dfe70bd6.so.1
wtg_cli.libs/libkrb5-fcafa220.so.3
wtg_cli.libs/libkrb5support-d0bcff84.so.0
wtg_cli.libs/libpcre-9513aab5.so.1
wtg_cli.libs/libselinux-0922c95c.so.1
wtg_cli.libs/libssl-cd1d6220.so.10
wtg_cli-0.3.0.dist-info/RECORD
