Metadata-Version: 2.4
Name: wtg-cli
Version: 0.3.0
Classifier: Programming Language :: Python :: 3
Classifier: Programming Language :: Rust
Classifier: License :: OSI Approved :: MIT License
Classifier: Operating System :: OS Independent
Classifier: Topic :: Software Development :: Version Control :: Git
License-File: LICENSE
Summary: What The Git CLI – snarky Git history sleuth packaged for Python
Author: Mike Perlov
License: MIT
Requires-Python: >=3.9
